[
    {
        "ID": 1,
        "Номер банкомата": 652100,
        "Адрес банкомата": "Раушская набережная, 10/2",
        "Coordinates": [
            55.7475203364008,
            37.63094829830495
        ]
    },
    {
        "ID": 2,
        "Номер банкомата": 652101,
        "Адрес банкомата": "Солянский тупик",
        "Coordinates": [
            55.75371064146499,
            37.63550061830072
        ]
    },
    {
        "ID": 3,
        "Номер банкомата": 652102,
        "Адрес банкомата": "улица Большая Дмитровка, 5/6с5",
        "Coordinates": [
            55.760109077362586,
            37.61539868089607
        ]
    },
    {
        "ID": 4,
        "Номер банкомата": 652103,
        "Адрес банкомата": "парк Зарядье",
        "Coordinates": [
            55.75132678244861,
            37.62761192384487
        ]
    },
    {
        "ID": 5,
        "Номер банкомата": 652104,
        "Адрес банкомата": "парк Зарядье",
        "Coordinates": [
            55.75026647660128,
            37.63003807154849
        ]
    },
    {
        "ID": 6,
        "Номер банкомата": 652105,
        "Адрес банкомата": "улица Охотный Ряд, 1",
        "Coordinates": [
            55.75771285507231,
            37.61552961469896
        ]
    },
    {
        "ID": 7,
        "Номер банкомата": 652106,
        "Адрес банкомата": "Новая площадь, 3/4",
        "Coordinates": [
            55.75787673436656,
            37.62913288470771
        ]
    },
    {
        "ID": 8,
        "Номер банкомата": 652107,
        "Адрес банкомата": "Тверская улица",
        "Coordinates": [
            55.75704233117703,
            37.61471372015719
        ]
    },
    {
        "ID": 9,
        "Номер банкомата": 652108,
        "Адрес банкомата": "Новая площадь, 3/4",
        "Coordinates": [
            55.757511156501295,
            37.62997207438889
        ]
    },
    {
        "ID": 10,
        "Номер банкомата": 652109,
        "Адрес банкомата": "Лубянский проезд, 3/6с17",
        "Coordinates": [
            55.75920174349848,
            37.62903325542316
        ]
    },
    {
        "ID": 11,
        "Номер банкомата": 652110,
        "Адрес банкомата": "Москворецкая набережная",
        "Coordinates": [
            55.74867739271906,
            37.63636561454887
        ]
    },
    {
        "ID": 12,
        "Номер банкомата": 652111,
        "Адрес банкомата": "Театральная площадь",
        "Coordinates": [
            55.75802017155908,
            37.62084056386344
        ]
    },
    {
        "ID": 13,
        "Номер банкомата": 652112,
        "Адрес банкомата": "улица Большая Лубянка, 14с1",
        "Coordinates": [
            55.7625367612576,
            37.62897013358161
        ]
    },
    {
        "ID": 14,
        "Номер банкомата": 652113,
        "Адрес банкомата": "Лучников переулок, 7/4с6",
        "Coordinates": [
            55.759204,
            37.63117082127
        ]
    },
    {
        "ID": 15,
        "Номер банкомата": 652114,
        "Адрес банкомата": "улица Балчуг, 7",
        "Coordinates": [
            55.746976612887366,
            37.62643509928672
        ]
    },
    {
        "ID": 16,
        "Номер банкомата": 652115,
        "Адрес банкомата": "Театральная площадь, 5с2",
        "Coordinates": [
            55.75703060044278,
            37.6204167404528
        ]
    },
    {
        "ID": 17,
        "Номер банкомата": 652116,
        "Адрес банкомата": "улица Ильинка, 23/16",
        "Coordinates": [
            55.75684415604147,
            37.62889422097155
        ]
    },
    {
        "ID": 18,
        "Номер банкомата": 652117,
        "Адрес банкомата": "Новая площадь, 8с1",
        "Coordinates": [
            55.75842285834186,
            37.62701236235614
        ]
    },
    {
        "ID": 19,
        "Номер банкомата": 652118,
        "Адрес банкомата": "Славянская площадь, 2/5/4",
        "Coordinates": [
            55.75345680939785,
            37.63507241351339
        ]
    },
    {
        "ID": 20,
        "Номер банкомата": 652119,
        "Адрес банкомата": "парк Свибловские пруды",
        "Coordinates": [
            55.85199820466464,
            37.63046131885913
        ]
    },
    {
        "ID": 21,
        "Номер банкомата": 652120,
        "Адрес банкомата": "Садовническая улица, 11с15",
        "Coordinates": [
            55.74752077566537,
            37.63171330731491
        ]
    },
    {
        "ID": 22,
        "Номер банкомата": 652121,
        "Адрес банкомата": "Армянский переулок, 2с2",
        "Coordinates": [
            55.76059512213491,
            37.634217141511805
        ]
    },
    {
        "ID": 23,
        "Номер банкомата": 652122,
        "Адрес банкомата": "Старая площадь, 10",
        "Coordinates": [
            55.755424315736384,
            37.63043709037506
        ]
    },
    {
        "ID": 24,
        "Номер банкомата": 652123,
        "Адрес банкомата": "Богоявленский переулок, 2/6с9",
        "Coordinates": [
            55.7558281071574,
            37.62259038255078
        ]
    },
    {
        "ID": 25,
        "Номер банкомата": 652124,
        "Адрес банкомата": "Лубочный переулок, 2",
        "Coordinates": [
            55.74683392110443,
            37.62528382225543
        ]
    },
    {
        "ID": 26,
        "Номер банкомата": 652125,
        "Адрес банкомата": "улица Варварка, 7/11/14с1",
        "Coordinates": [
            55.75286700152479,
            37.63007838837343
        ]
    },
    {
        "ID": 27,
        "Номер банкомата": 652126,
        "Адрес банкомата": "улица Ильинка, 10/2с1",
        "Coordinates": [
            55.75554426166136,
            37.62767786146355
        ]
    },
    {
        "ID": 28,
        "Номер банкомата": 652127,
        "Адрес банкомата": "улица Крузенштерна, 9",
        "Coordinates": [
            55.75266676360151,
            37.6998329211732
        ]
    },
    {
        "ID": 29,
        "Номер банкомата": 652128,
        "Адрес банкомата": "Суворовский парк",
        "Coordinates": [
            55.746706271202,
            37.43349362968974
        ]
    },
    {
        "ID": 30,
        "Номер банкомата": 652129,
        "Адрес банкомата": "4-я улица Марьиной Рощи, 4А",
        "Coordinates": [
            55.7948969285499,
            37.62502165289508
        ]
    },
    {
        "ID": 0,
        "Номер банкомата": 652130,
        "Адрес банкомата": "Тайникцкий сад",
        "Coordinates": [
            55.74982053127155,
            37.61840011650956
        ]
    },
    {
        "ID": 32,
        "Номер банкомата": 652131,
        "Адрес банкомата": "2-й Раушский переулок, 4А",
        "Coordinates": [
            55.74683564435074,
            37.63454692557049
        ]
    },
    {
        "ID": 33,
        "Номер банкомата": 652132,
        "Адрес банкомата": "Большой Черкасский переулок, 2/10",
        "Coordinates": [
            55.75723506011673,
            37.62567649899953
        ]
    },
    {
        "ID": 34,
        "Номер банкомата": 652133,
        "Адрес банкомата": "улица Большая Дмитровка, 7/5с5",
        "Coordinates": [
            55.76080224368873,
            37.61355431036532
        ]
    },
    {
        "ID": 35,
        "Номер банкомата": 652134,
        "Адрес банкомата": "Кривоколенный переулок, 10с9",
        "Coordinates": [
            55.76127643685645,
            37.636439679025926
        ]
    },
    {
        "ID": 36,
        "Номер банкомата": 652135,
        "Адрес банкомата": "улица Большая Дмитровка, 11",
        "Coordinates": [
            55.76189169894588,
            37.61392787767544
        ]
    },
    {
        "ID": 37,
        "Номер банкомата": 652136,
        "Адрес банкомата": "Садовническая улица, 6с11",
        "Coordinates": [
            55.74741184706157,
            37.62662661072608
        ]
    },
    {
        "ID": 38,
        "Номер банкомата": 652137,
        "Адрес банкомата": "Проектируемый проезд № 1166",
        "Coordinates": [
            55.75688404404313,
            37.46908650904677
        ]
    },
    {
        "ID": 39,
        "Номер банкомата": 652138,
        "Адрес банкомата": "Новая площадь, 12с4",
        "Coordinates": [
            55.75748567475624,
            37.62738859065292
        ]
    },
    {
        "ID": 40,
        "Номер банкомата": 652139,
        "Адрес банкомата": "Красная площадь, 3",
        "Coordinates": [
            55.75418670132981,
            37.62119262606446
        ]
    },
    {
        "ID": 41,
        "Номер банкомата": 652140,
        "Адрес банкомата": "Кремлевская набережная",
        "Coordinates": [
            55.74893804520856,
            37.62009187695681
        ]
    },
    {
        "ID": 42,
        "Номер банкомата": 652141,
        "Адрес банкомата": "улица Балчуг, 1",
        "Coordinates": [
            55.74863685026581,
            37.625772202183086
        ]
    },
    {
        "ID": 43,
        "Номер банкомата": 652142,
        "Адрес банкомата": "Китайгородский проезд",
        "Coordinates": [
            55.75376896024591,
            37.6337355118313
        ]
    },
    {
        "ID": 44,
        "Номер банкомата": 652143,
        "Адрес банкомата": "Красная площадь, 5",
        "Coordinates": [
            55.75317783632758,
            37.62282633662248
        ]
    },
    {
        "ID": 45,
        "Номер банкомата": 652144,
        "Адрес банкомата": "улица Крылатские Холмы, 7к2",
        "Coordinates": [
            55.74908984613051,
            37.42331289049186
        ]
    },
    {
        "ID": 46,
        "Номер банкомата": 652145,
        "Адрес банкомата": "Малый Златоустинский переулок, 3с3",
        "Coordinates": [
            55.75857534833134,
            37.63368621297522
        ]
    },
    {
        "ID": 47,
        "Номер банкомата": 652146,
        "Адрес банкомата": "Садовническая набережная, 7",
        "Coordinates": [
            55.74665046118419,
            37.62763115120861
        ]
    },
    {
        "ID": 48,
        "Номер банкомата": 652147,
        "Адрес банкомата": "Варшавское шоссе, 87Б",
        "Coordinates": [
            55.653550625865,
            37.620546936516114
        ]
    },
    {
        "ID": 49,
        "Номер банкомата": 652148,
        "Адрес банкомата": "улица Большая Дмитровка, 2",
        "Coordinates": [
            55.75885285653851,
            37.61778038499971
        ]
    },
    {
        "ID": 50,
        "Номер банкомата": 652149,
        "Адрес банкомата": "Большой Черкасский переулок, 13с4",
        "Coordinates": [
            55.7571195446405,
            37.62760605453734
        ]
    },
    {
        "ID": 51,
        "Номер банкомата": 652150,
        "Адрес банкомата": "Спасская улица",
        "Coordinates": [
            55.75094592560011,
            37.61912643028884
        ]
    },
    {
        "ID": 52,
        "Номер банкомата": 652151,
        "Адрес банкомата": "Красная площадь, 3",
        "Coordinates": [
            55.75431765315787,
            37.62041856330451
        ]
    },
    {
        "ID": 53,
        "Номер банкомата": 652152,
        "Адрес банкомата": "ул. Варварка, 6",
        "Coordinates": [
            55.74915813260228,
            37.627476692679465
        ]
    },
    {
        "ID": 54,
        "Номер банкомата": 652153,
        "Адрес банкомата": "Милютинский переулок, 5с2",
        "Coordinates": [
            55.762272,
            37.631502
        ]
    },
    {
        "ID": 55,
        "Номер банкомата": 652154,
        "Адрес банкомата": "улица Большая Дмитровка, 10с5",
        "Coordinates": [
            55.76148859846126,
            37.61598821488068
        ]
    },
    {
        "ID": 56,
        "Номер банкомата": 652155,
        "Адрес банкомата": "ул. Варварка, 6",
        "Coordinates": [
            55.751579,
            37.625765
        ]
    },
    {
        "ID": 57,
        "Номер банкомата": 652156,
        "Адрес банкомата": "2-й Раушский переулок, 1-3/26с15",
        "Coordinates": [
            55.74695592771815,
            37.63625947432407
        ]
    },
    {
        "ID": 58,
        "Номер банкомата": 652157,
        "Адрес банкомата": "Мясницкая улица, 22с1",
        "Coordinates": [
            55.7623118201598,
            37.63445965701822
        ]
    },
    {
        "ID": 59,
        "Номер банкомата": 652158,
        "Адрес банкомата": "Красная площадь, 3",
        "Coordinates": [
            55.75462341837928,
            37.6214855043629
        ]
    },
    {
        "ID": 60,
        "Номер банкомата": 652159,
        "Адрес банкомата": "Никольская улица, 19-21с3",
        "Coordinates": [
            55.758937473766046,
            37.62388019872449
        ]
    },
    {
        "ID": 61,
        "Номер банкомата": 652160,
        "Адрес банкомата": "Солянский пр., 1",
        "Coordinates": [
            55.754076,
            37.635664
        ]
    },
    {
        "ID": 62,
        "Номер банкомата": 652161,
        "Адрес банкомата": "Мясницкая улица, 13с3",
        "Coordinates": [
            55.76257864850788,
            37.634491466482345
        ]
    },
    {
        "ID": 63,
        "Номер банкомата": 652162,
        "Адрес банкомата": "улица Большая Дмитровка, 7/5с3",
        "Coordinates": [
            55.76074229448146,
            37.6138704069779
        ]
    },
    {
        "ID": 64,
        "Номер банкомата": 652163,
        "Адрес банкомата": "улица Маросейка, 11/4с1",
        "Coordinates": [
            55.75792076505748,
            37.63609963199456
        ]
    },
    {
        "ID": 65,
        "Номер банкомата": 652164,
        "Адрес банкомата": "\r\nСофийская наб., 30, стр. 1",
        "Coordinates": [
            55.747936,
            37.621381
        ]
    },
    {
        "ID": 66,
        "Номер банкомата": 652165,
        "Адрес банкомата": "улица Маросейка, 8",
        "Coordinates": [
            55.75758772004348,
            37.636323980663136
        ]
    },
    {
        "ID": 67,
        "Номер банкомата": 652166,
        "Адрес банкомата": "Второй кассационный суд общей юрисдикции",
        "Coordinates": [
            55.74658,
            37.61349
        ]
    },
    {
        "ID": 68,
        "Номер банкомата": 652167,
        "Адрес банкомата": "\r\nМосфильмовская ул., 17/25",
        "Coordinates": [
            55.715601,
            37.516413
        ]
    },
    {
        "ID": 69,
        "Номер банкомата": 652168,
        "Адрес банкомата": "ул. Дружбы, 6",
        "Coordinates": [
            55.710773,
            37.516386
        ]
    },
    {
        "ID": 70,
        "Номер банкомата": 652169,
        "Адрес банкомата": "Ломоносовский проспект, 27к7",
        "Coordinates": [
            55.69473,
            37.524622
        ]
    },
    {
        "ID": 71,
        "Номер банкомата": 652170,
        "Адрес банкомата": "\r\nКировоградская ул., 14",
        "Coordinates": [
            55.622609,
            37.605939
        ]
    },
    {
        "ID": 72,
        "Номер банкомата": 652171,
        "Адрес банкомата": "1-й Дорожный пр., 4, стр. 1",
        "Coordinates": [
            55.614053,
            37.616979
        ]
    },
    {
        "ID": 73,
        "Номер банкомата": 652172,
        "Адрес банкомата": "Дорожная ул., 3, корп. 19",
        "Coordinates": [
            55.611689,
            37.627319
        ]
    },
    {
        "ID": 74,
        "Номер банкомата": 652173,
        "Адрес банкомата": "ул. Речников, 25",
        "Coordinates": [
            55.677539,
            37.689752
        ]
    },
    {
        "ID": 75,
        "Номер банкомата": 652174,
        "Адрес банкомата": "\r\nКоломенская ул., 7",
        "Coordinates": [
            55.682128,
            37.702885
        ]
    },
    {
        "ID": 76,
        "Номер банкомата": 652175,
        "Адрес банкомата": "ул. Гурьянова, 4, корп. 3",
        "Coordinates": [
            55.691937,
            37.719747
        ]
    },
    {
        "ID": 77,
        "Номер банкомата": 652176,
        "Адрес банкомата": "\r\nШоссейная ул., 2Б",
        "Coordinates": [
            55.700679,
            37.726331
        ]
    },
    {
        "ID": 78,
        "Номер банкомата": 652177,
        "Адрес банкомата": "\r\nКраснодарская ул., 51",
        "Coordinates": [
            55.677341,
            37.765408
        ]
    },
    {
        "ID": 79,
        "Номер банкомата": 652178,
        "Адрес банкомата": "\r\nул. Перерва, 90",
        "Coordinates": [
            55.67422,
            37.791109
        ]
    },
    {
        "ID": 80,
        "Номер банкомата": 652179,
        "Адрес банкомата": "\r\nСаввинская ул., 15",
        "Coordinates": [
            55.727557,
            38.033178
        ]
    },
    {
        "ID": 81,
        "Номер банкомата": 652180,
        "Адрес банкомата": "\r\nул. Калинина, 12",
        "Coordinates": [
            55.740928,
            38.030303
        ]
    },
    {
        "ID": 82,
        "Номер банкомата": 652181,
        "Адрес банкомата": "\r\nСоветская ул., 54",
        "Coordinates": [
            55.750783,
            38.041622
        ]
    },
    {
        "ID": 83,
        "Номер банкомата": 652182,
        "Адрес банкомата": "просп. Мира, 119, стр. 56",
        "Coordinates": [
            55.836049,
            37.624355
        ]
    },
    {
        "ID": 84,
        "Номер банкомата": 652183,
        "Адрес банкомата": "\r\nДонская ул., 43, стр. 3",
        "Coordinates": [
            55.716564,
            37.605768
        ]
    },
    {
        "ID": 85,
        "Номер банкомата": 652184,
        "Адрес банкомата": "Электродная улица, 2с1",
        "Coordinates": [
            55.757024,
            37.750793
        ]
    },
    {
        "ID": 86,
        "Номер банкомата": 652185,
        "Адрес банкомата": "Электродный переулок, 7",
        "Coordinates": [
            55.749506,
            37.751709
        ]
    },
    {
        "ID": 87,
        "Номер банкомата": 652186,
        "Адрес банкомата": "2-й Грайвороновский проезд, 38к1",
        "Coordinates": [
            55.724342,
            37.740938
        ]
    },
    {
        "ID": 88,
        "Номер банкомата": 652187,
        "Адрес банкомата": "Угрешская улица, 33с24",
        "Coordinates": [
            55.716646,
            37.699193
        ]
    },
    {
        "ID": 89,
        "Номер банкомата": 652188,
        "Адрес банкомата": "Южнопортовая улица, 22с1",
        "Coordinates": [
            55.705654,
            37.688807
        ]
    },
    {
        "ID": 90,
        "Номер банкомата": 652189,
        "Адрес банкомата": "улица Трофимова, 32к1",
        "Coordinates": [
            55.702191,
            37.684865
        ]
    },
    {
        "ID": 91,
        "Номер банкомата": 652190,
        "Адрес банкомата": "улица Новинки, 31",
        "Coordinates": [
            55.67655,
            37.678164
        ]
    },
    {
        "ID": 92,
        "Номер банкомата": 652191,
        "Адрес банкомата": "Севанская улица, 3к2",
        "Coordinates": [
            55.619142,
            37.662434
        ]
    },
    {
        "ID": 93,
        "Номер банкомата": 652192,
        "Адрес банкомата": "улица Красного Маяка, 16",
        "Coordinates": [
            55.6135,
            37.586774
        ]
    },
    {
        "ID": 94,
        "Номер банкомата": 652193,
        "Адрес банкомата": "улица Орджоникидзе, 11с1А",
        "Coordinates": [
            55.707791,
            37.595806
        ]
    },
    {
        "ID": 95,
        "Номер банкомата": 652194,
        "Адрес банкомата": "Старая площадь, 10/4с1",
        "Coordinates": [
            55.75359,
            37.631909
        ]
    },
    {
        "ID": 96,
        "Номер банкомата": 652195,
        "Адрес банкомата": "улица Варварка, 6с1",
        "Coordinates": [
            55.75167,
            37.629053
        ]
    },
    {
        "ID": 97,
        "Номер банкомата": 652196,
        "Адрес банкомата": "Лубянский проезд, 5с1",
        "Coordinates": [
            55.75853100588982,
            37.629515705690345
        ]
    },
    {
        "ID": 98,
        "Номер банкомата": 652197,
        "Адрес банкомата": "Неглинная улица, 6/2с2",
        "Coordinates": [
            55.76045793444417,
            37.621604944285295
        ]
    },
    {
        "ID": 99,
        "Номер банкомата": 652198,
        "Адрес банкомата": "Петроверигский переулок, 4с4",
        "Coordinates": [
            55.756396,
            37.636805
        ]
    },
    {
        "ID": 100,
        "Номер банкомата": 652199,
        "Адрес банкомата": "Малый Златоустинский переулок, 10с2",
        "Coordinates": [
            55.75909748204513,
            37.63586896025052
        ]
    }
]